MANIFEST.in
setup.py
eagertools/__init__.py
eagertools/consume.py
eagertools/eager.py
eagertools.egg-info/PKG-INFO
eagertools.egg-info/SOURCES.txt
eagertools.egg-info/dependency_links.txt
eagertools.egg-info/top_level.txt