Metadata-Version: 1.1
Name: eagertools
Version: 0.4
Summary: Eager version of some lazy functions.
Home-page: http://github.com/abingham/eagertools
Author: Austin Bingham
Author-email: austin.bingham@gmail.com
License: MIT
Keywords: functional
Platform: any
Classifier: Development Status :: 4 - Beta
Classifier: Environment :: Console
Classifier: Intended Audience :: Developers
Classifier: License :: OSI Approved :: MIT License
Classifier: Operating System :: OS Independent
Classifier: Programming Language :: Python
Classifier: Topic :: Software Development :: Libraries
